LICENSE
README.rst
setup.py
xtokenizer/__init__.py
xtokenizer/_tokenizer.py
xtokenizer/stats.py
xtokenizer/utils.py
xtokenizer.egg-info/PKG-INFO
xtokenizer.egg-info/SOURCES.txt
xtokenizer.egg-info/dependency_links.txt
xtokenizer.egg-info/not-zip-safe
xtokenizer.egg-info/requires.txt
xtokenizer.egg-info/top_level.txt