Metadata-Version: 2.1
Name: xtokenizer
Version: 0.0.4
Summary: A simple Tokenizer
Home-page: https://gitee.com/summry/xtokenizer
Author: summy
Author-email: fkfkfk2024@2925.com
License: UNKNOWN
Keywords: tokenizer,NLP
Platform: UNKNOWN
Requires-Python: >=3.6
License-File: LICENSE
